pret/__init__.py
pret/hooks.py
pret/ipython_var_cleaner.py
pret/main.py
pret/manager.py
pret/marshal.py
pret/react.py
pret/render.py
pret/routing.py
pret/serve.py
pret/store.py
pret/webpack.standalone.js
pret/cli/__init__.py
pret/cli/generate-py-stubs.js
pret/cli/prepack_command.py
pret/cli/stub_command.py
pret/cli/update_jupyter_config.py
pret/js-base/bundle.92134595ee03c5f7482f.js
pret/js-base/index.html
pret/js-extension/build_log.json
pret/js-extension/package.json
pret/js-extension/schemas/pret/package.json.orig
pret/js-extension/schemas/pret/pret.json
pret/js-extension/static/client_index_tsx.babee5811e387252fdce.js
pret/js-extension/static/client_index_tsx.babee5811e387252fdce.js.map
pret/js-extension/static/client_jupyter_plugin_tsx.b0f24f773ba81a38c989.js
pret/js-extension/static/client_jupyter_plugin_tsx.b0f24f773ba81a38c989.js.map
pret/js-extension/static/remoteEntry.8cd7bc17f76e5913822a.js
pret/js-extension/static/remoteEntry.8cd7bc17f76e5913822a.js.map
pret/js-extension/static/style.js
pret/js-extension/static/vendors-node_modules_css-loader_dist_runtime_api_js-node_modules_css-loader_dist_runtime_sour-4125d8.ca7b28ab69748722439e.js
pret/js-extension/static/vendors-node_modules_css-loader_dist_runtime_api_js-node_modules_css-loader_dist_runtime_sour-4125d8.ca7b28ab69748722439e.js.map
pret/js-extension/static/vendors-node_modules_react-router-dom_dist_index_js.a904a7cddd6a38151398.js
pret/js-extension/static/vendors-node_modules_react-router-dom_dist_index_js.a904a7cddd6a38151398.js.map
pret/js-extension/static/vendors-node_modules_react-router_dist_index_js.43512cc9f7e894e67669.js
pret/js-extension/static/vendors-node_modules_react-router_dist_index_js.43512cc9f7e894e67669.js.map
pret/js-extension/static/vendors-node_modules_react_jsx-runtime_js.a484436cafd1845fe9cc.js
pret/js-extension/static/vendors-node_modules_react_jsx-runtime_js.a484436cafd1845fe9cc.js.map
pret-0.5.2.dist-info/METADATA
pret-0.5.2.dist-info/WHEEL
pret-0.5.2.dist-info/entry_points.txt
pret-0.5.2.dist-info/licenses/LICENSE
pret-0.5.2.dist-info/RECORD
