Metadata-Version: 2.4
Name: pret
Version: 0.5.2
Summary: Python framework to build reactive web apps with seamless server-client interaction
Project-URL: homepage, https://github.com/percevalw/pret/
Project-URL: repository, https://github.com/percevalw/pret/
Author-email: Perceval Wajsburt <perceval.wajsburt@gmail.com>
License:                                  Apache License
License-File: LICENSE
Classifier: Development Status :: 4 - Beta
Classifier: Framework :: Jupyter
Classifier: Framework :: Jupyter :: JupyterLab
Classifier: Framework :: Jupyter :: JupyterLab :: 3
Classifier: Framework :: Jupyter :: JupyterLab :: 4
Classifier: Framework :: Jupyter :: JupyterLab :: Extensions :: Mime Renderers
Classifier: Framework :: Jupyter :: JupyterLab :: Extensions :: Prebuilt
Classifier: Intended Audience :: Developers
Classifier: Intended Audience :: Science/Research
Classifier: License :: OSI Approved :: Apache Software License
Classifier: Programming Language :: Python :: 3
Classifier: Programming Language :: Python :: 3 :: Only
Classifier: Programming Language :: Python :: 3.7
Classifier: Programming Language :: Python :: 3.8
Classifier: Programming Language :: Python :: 3.9
Classifier: Programming Language :: Python :: 3.10
Classifier: Topic :: Scientific/Engineering :: Visualization
Classifier: Topic :: Software Development :: Libraries
Classifier: Topic :: Software Development :: Libraries :: Application Frameworks
Classifier: Topic :: Software Development :: Libraries :: Python Modules
Classifier: Topic :: Software Development :: User Interfaces
Classifier: Topic :: Software Development :: Widget Sets
Requires-Python: !=3.8.1,<4.0,>=3.7
Requires-Dist: cbor2
Requires-Dist: ipykernel
Requires-Dist: pret-pycrdt>=0.12.20-post2
Requires-Dist: pygetsource
Requires-Dist: quart
Requires-Dist: typer
Requires-Dist: watchfiles
Provides-Extra: joy
Requires-Dist: pret-joy; extra == 'joy'
